{  
    "title" : "IDOLiSH7",
    "season" : "Season 3 - Third BEAT!",
    "episodes" : {
        "E1 - Clouds Covering the Stars" : "https://www.crunchyroll.com/watch/G7PU4WWZQ/clouds-covering-the-stars",
        "E2 - Unknown Scars" : "https://www.crunchyroll.com/watch/G9DUEDDQ3/unknown-scars",
        "E3 - Rifts" : "https://www.crunchyroll.com/watch/GX9UQKKGZ/rifts",
        "E4 - The Voice Within" : "https://www.crunchyroll.com/watch/G4VUQMMJ1/the-voice-within",
        "E5 - Where We Belong" : "https://www.crunchyroll.com/watch/G14U4XX01/where-we-belong",
        "E6 - Feelings to Convey" : "https://www.crunchyroll.com/watch/GJWU2JJGW/feelings-to-convey",
        "E7 - Contact" : "https://www.crunchyroll.com/watch/GN7UDWWEX/contact",
        "E8 - Our Incomplete Selves" : "https://www.crunchyroll.com/watch/GK9U388J2/our-incomplete-selves",
        "E9 - Re:vale" : "https://www.crunchyroll.com/watch/GMKUX5523/revale",
        "E10 - The Training Camp Begins!" : "https://www.crunchyroll.com/watch/GVWU0PPE0/the-training-camp-begins",
        "E11 - Meticulous Malice" : "https://www.crunchyroll.com/watch/G31UX771V/meticulous-malice",
        "E12 - Preparing to Take Over" : "https://www.crunchyroll.com/watch/GPWUK007M/preparing-to-take-over",
        "E13 - Tetrarchy of Madness and Destruction" : "https://www.crunchyroll.com/watch/G2XU055KP/tetrarchy-of-madness-and-destruction",
        "E14 - Threat" : "https://www.crunchyroll.com/watch/GN7UDEVKJ/threat",
        "E15 - Indestructible Soul" : "https://www.crunchyroll.com/watch/GK9U3JD23/indestructible-soul",
        "E16 - The Angel and the Monster" : "https://www.crunchyroll.com/watch/G50UZP1NM/the-angel-and-the-monster",
        "E17 - Comeback Play" : "https://www.crunchyroll.com/watch/GWDU8XQM0/comeback-play",
        "E18 - Dear Butterfly" : "https://www.crunchyroll.com/watch/GG1U29Z5P/dear-butterfly",
        "E19 - The Trio's Resolve" : "https://www.crunchyroll.com/watch/G0DUNPJWV/the-trios-resolve",
        "E20 - Together We'll Dream a Neverending Dream" : "https://www.crunchyroll.com/watch/GEVUZMN35/together-well-dream-a-neverending-dream",
        "E21 - Bonds and Promises" : "https://www.crunchyroll.com/watch/G7PU4EJ25/bonds-and-promises",
        "E22 - Anytime, Anywhere" : "https://www.crunchyroll.com/watch/G9DUEJGND/anytime-anywhere",
        "E23 - The Resolve to Keep Singing" : "https://www.crunchyroll.com/watch/GX9UQXZM7/the-resolve-to-keep-singing",
        "E24 - Begin the Counterattack" : "https://www.crunchyroll.com/watch/G4VUQ980Z/begin-the-counterattack",
        "E25 - Behind-the-Scenes Meeting" : "https://www.crunchyroll.com/watch/G14U4DGJW/behind-the-scenes-meeting",
        "E26 - Friends Day!" : "https://www.crunchyroll.com/watch/GJWU23E7G/friends-day",
        "E27 - Attractive Force" : "https://www.crunchyroll.com/watch/G31UX9QVP/attractive-force",
        "E28 - Changing Scenery" : "https://www.crunchyroll.com/watch/G69P3171Y/from-now-on",
        "E29 - Stir and Spill Over" : "https://www.crunchyroll.com/watch/G2XU0QJN3/stir-and-spill-over",
        "E30 - Bound Fates" : "https://www.crunchyroll.com/watch/G8WUNME7E/bound-fates"
    }
}
